<?xml version="1.0"?>
<!DOCTYPE hibernate-mapping PUBLIC
    "-//Hibernate/Hibernate Mapping DTD//EN"
    "http://hibernate.sourceforge.net/hibernate-mapping-2.0.dtd" >
    
<hibernate-mapping>

<!-- 
    Created by Middlegen Hibernate plugin

    http://boss.bekk.no/boss/middlegen/
    http://hibernate.sourceforge.net/
-->

<class 
    name="com.netpace.aims.model.application.AimsAppFiles" 
    table="AIMS_APPS"
>
	<meta attribute="extends">com.netpace.aims.model.BaseValueObject</meta>    
    <id
        name="appsId"
        type="java.lang.Long"
        column="APPS_ID"
    >
        <generator class="sequence">
			<param name="sequence">SEQ_PK_APPS</param>
		</generator>
    </id>
    <property
        name="flashDemo"
        type="java.sql.Blob"
        column="FLASH_DEMO"
        length="4000"
    />
    <property
        name="userGuide"
        type="java.sql.Blob"
        column="USER_GUIDE"
        length="4000"
    />
    <property
        name="screenJpeg"
        type="java.sql.Blob"
        column="SCREEN_JPEG"        
        length="4000"
    />
    <property
        name="splashScreenEps"
        type="java.sql.Blob"
        column="SPLASH_SCREEN_EPS"
        length="4000"
    />
    <property
        name="activeScreenEps"
        type="java.sql.Blob"
        column="ACTIVE_SCREEN_EPS"
        length="4000"
    />    
    <property
        name="faqDoc"
        type="java.sql.Blob"
        column="FAQ_DOC"
        length="4000"
    />
    <property
        name="testPlanResults"
        type="java.sql.Blob"
        column="TEST_PLAN_RESULTS"
        length="4000"
    />

    <property
        name="screenJpegFileName"
        type="java.lang.String"
        column="SCREEN_JPEG_FILE_NAME"
        length="150"
    />
    <property
        name="screenJpegContentType"
        type="java.lang.String"
        column="SCREEN_JPEG_CONTENT_TYPE"
        length="100"
    />
    <property
        name="activeScreenEpsFileName"
        type="java.lang.String"
        column="ACTIVE_SCREEN_EPS_FILE_NAME"
        length="150"
    />
    <property
        name="activeScreenEpsContentType"
        type="java.lang.String"
        column="ACTIVE_SCREEN_EPS_CONTENT_TYPE"
        length="100"
    />
    <property
        name="flashDemoFileName"
        type="java.lang.String"
        column="FLASH_DEMO_FILE_NAME"
        length="150"
    />
    <property
        name="flashDemoContentType"
        type="java.lang.String"
        column="FLASH_DEMO_CONTENT_TYPE"
        length="100"
    />
    <property
        name="splashScreenEpsFileName"
        type="java.lang.String"
        column="SPLASH_SCREEN_EPS_FILE_NAME"
        length="150"
    />
    <property
        name="splashScreenEpsContentType"
        type="java.lang.String"
        column="SPLASH_SCREEN_EPS_CONTENT_TYPE"
        length="100"
    />
    <property
        name="userGuideFileName"
        type="java.lang.String"
        column="USER_GUIDE_FILE_NAME"
        length="150"
    />
    <property
        name="userGuideContentType"
        type="java.lang.String"
        column="USER_GUIDE_CONTENT_TYPE"
        length="100"
    />
    <property
        name="faqDocFileName"
        type="java.lang.String"
        column="FAQ_DOC_FILE_NAME"
        length="150"
    />
    <property
        name="faqDocContentType"
        type="java.lang.String"
        column="FAQ_DOC_CONTENT_TYPE"
        length="100"
    />    
    <property
        name="testPlanResultsFileName"
        type="java.lang.String"
        column="TEST_PLAN_RESULTS_FILE_NAME"
        length="150"
    />
    <property
        name="testPlanResultsContentType"
        type="java.lang.String"
        column="TEST_PLAN_RESULTS_CONTENT_TYPE"
        length="100"
    />
    <property
        name="screenJpeg2"
        type="java.sql.Blob"
        column="SCREEN_JPEG_2"
        length="4000"
    />
    <property
        name="screenJpeg3"
        type="java.sql.Blob"
        column="SCREEN_JPEG_3"
        length="4000"
    />
    <property
        name="screenJpeg4"
        type="java.sql.Blob"
        column="SCREEN_JPEG_4"
        length="4000"
    />
    <property
        name="screenJpeg5"
        type="java.sql.Blob"
        column="SCREEN_JPEG_5"
        length="4000"
    />
    <property
        name="screenJpeg2FileName"
        type="java.lang.String"
        column="SCREEN_JPEG_2_FILE_NAME"
        length="150"
    />
    <property
        name="screenJpeg3FileName"
        type="java.lang.String"
        column="SCREEN_JPEG_3_FILE_NAME"
        length="150"
    />
    <property
        name="screenJpeg4FileName"
        type="java.lang.String"
        column="SCREEN_JPEG_4_FILE_NAME"
        length="150"
    />
    <property
        name="screenJpeg5FileName"
        type="java.lang.String"
        column="SCREEN_JPEG_5_FILE_NAME"
        length="150"
    />
    <property
        name="screenJpeg2ContentType"
        type="java.lang.String"
        column="SCREEN_JPEG_2_CONTENT_TYPE"
        length="100"
    />
    <property
        name="screenJpeg3ContentType"
        type="java.lang.String"
        column="SCREEN_JPEG_3_CONTENT_TYPE"
        length="100"
    />
    <property
        name="screenJpeg4ContentType"
        type="java.lang.String"
        column="SCREEN_JPEG_4_CONTENT_TYPE"
        length="100"
    />
    <property
        name="screenJpeg5ContentType"
        type="java.lang.String"
        column="SCREEN_JPEG_5_CONTENT_TYPE"
        length="100"
    />    
</class>
</hibernate-mapping>


