 <taglib>
    <taglib-uri>struts-bean</taglib-uri>
    <taglib-location>/WEB-INF/struts-bean.tld</taglib-location>
 </taglib>

 <taglib>
    <taglib-uri>struts-html</taglib-uri>
    <taglib-location>/WEB-INF/struts-html.tld</taglib-location>
 </taglib>

 <taglib>
    <taglib-uri>struts-logic</taglib-uri>
    <taglib-location>/WEB-INF/struts-logic.tld</taglib-location>
 </taglib>

 <taglib>
    <taglib-uri>struts-template</taglib-uri>
    <taglib-location>/WEB-INF/struts-template.tld</taglib-location>
 </taglib>

  <taglib>
    <taglib-uri>/WEB-INF/tiles.tld</taglib-uri>
    <taglib-location>/WEB-INF/tiles.tld</taglib-location>
  </taglib>

 <taglib>
    <taglib-uri>aims</taglib-uri>
    <taglib-location>/WEB-INF/aims.tld</taglib-location>
 </taglib>
 
 <!-- For JSTL, Adnan Ahmed (10-Jan-2008) -->
     <taglib>
		<taglib-uri>/WEB-INF/c.tld</taglib-uri>
		<taglib-location>/WEB-INF/c.tld</taglib-location>
	</taglib>
	<taglib>
		<taglib-uri>/WEB-INF/c-rt.tld</taglib-uri>
		<taglib-location>/WEB-INF/c-rt.tld</taglib-location>
	</taglib>
	<taglib>
		<taglib-uri>/WEB-INF/fmt.tld</taglib-uri>
		<taglib-location>/WEB-INF/fmt.tld</taglib-location>
	</taglib>
	<taglib>
		<taglib-uri>/WEB-INF/fmt-rt.tld</taglib-uri>
		<taglib-location>/WEB-INF/fmt-rt.tld</taglib-location>
	</taglib>